{
  "id": "EUVD-2026-2657",
  "enisaUuid": "2349ef6b-09f3-3ac8-824c-1ad94ab22811",
  "description": "Malicious code in haqawi (PyPI)",
  "datePublished": "Jan 14, 2026, 9:16:14 PM",
  "dateUpdated": "Jan 19, 2026, 7:16:04 AM",
  "baseScore": 0.0,
  "references": [
    "https://www.virustotal.com/gui/file-analysis/NzcxYTcyZDQxMzc0ZDUwNTk4MDY4OTE3Y2U3MzdhNDY6MTc2NzQwMTQwOQ==",
    "https://bad-packages.kam193.eu/pypi/package/haqawi"
  ],
  "aliases": [
    "MAL-2026-255"
  ],
  "epss": 0.0,
  "enisaIdProduct": [],
  "enisaIdVendor": []
}